instance_cache.py
instance_cache-0.2.1.dist-info/licenses/LICENSE
instance_cache-0.2.1.dist-info/METADATA
instance_cache-0.2.1.dist-info/WHEEL
instance_cache-0.2.1.dist-info/top_level.txt
instance_cache-0.2.1.dist-info/RECORD
