Metadata-Version: 2.4
Name: instance_cache
Version: 0.2.1
Summary: 为类实例方法提供实例级的结果缓存, 不影响类实例正常垃圾回收的装饰器
Author-email: Liu Wei <23S112099@stu.hit.edu.cn>
Maintainer-email: Liu Wei <23S112099@stu.hit.edu.cn>
License: MIT License
Project-URL: Homepage, https://github.com/AomandeNiuma/instance_cache
Keywords: instance_cache,cache
Classifier: License :: OSI Approved :: MIT License
Classifier: Programming Language :: Python :: 3
Classifier: Programming Language :: Python :: 3.7
Classifier: Programming Language :: Python :: 3.8
Classifier: Programming Language :: Python :: 3.9
Classifier: Programming Language :: Python :: 3.10
Classifier: Programming Language :: Python :: 3.11
Classifier: Programming Language :: Python :: 3.12
Classifier: Programming Language :: Python :: 3.13
Requires-Python: >=3.7.0
License-File: LICENSE
Dynamic: license-file
